calibre_search/__init__.py
calibre_search/calibre_search.py
calibre_search/lib/__init__.py
calibre_search/lib/amazon_link.py
calibre_search/lib/bing_image_search.py
calibre_search/lib/bing_stepper.py
calibre_search/lib/bn.py
calibre_search/lib/goodreads.py
calibre_search/lib/libgen.py
calibre_search/lib/thehiddenbay.py
calibre_search/lib/youtube.py
calibre_search/tests/__init__.py
calibre_search/tests/test_book_obj.py
calibre_search/tests/test_calibre_tooling.py
calibre_search-0.3.7.dist-info/METADATA
calibre_search-0.3.7.dist-info/WHEEL
calibre_search-0.3.7.dist-info/top_level.txt
calibre_search-0.3.7.dist-info/RECORD
