Metadata-Version: 2.1
Name: calibre-search
Version: 0.3.7
Summary: Search local Calibre XML export, lookup results online.
Home-page: https://github.com/taext/calibre_search
Author: David Mekonnen Rønn
Author-email: gh@v1d.dk
License: MIT
Download-URL: https://github.com/taext/calibre_search/archive/v0.3.7.tar.gz
Keywords: calibre jupyter
Platform: UNKNOWN
Classifier: Development Status :: 4 - Beta
Classifier: Intended Audience :: Information Technology
Classifier: Intended Audience :: Science/Research
Classifier: Natural Language :: English
Classifier: Programming Language :: Python :: 3
Classifier: License :: OSI Approved :: MIT License
Classifier: Operating System :: POSIX :: Linux
Classifier: Operating System :: Microsoft :: Windows :: Windows 10
